{
  "users": [
    {
      "id": "3869d2ac-ce23-4d52-af34-77e33e933f0c",
      "name": "lover",
      "userType": "NORMAL",
      "profileUrl": "https://cdn.fakercloud.com/avatars/okandungel_128.jpg"
    },
    {
      "id": "1ce378bc-14d0-4bd3-af0b-3aeb71a2119d",
      "name": "lover",
      "userType": "NORMAL",
      "profileUrl": "https://cdn.fakercloud.com/avatars/okandungel_128.jpg"
    },
    {
      "id": "535a7379-cfed-4222-8503-5bf326e33995",
      "name": "lover",
      "userType": "NORMAL",
      "profileUrl": "https://cdn.fakercloud.com/avatars/okandungel_128.jpg"
    },
    {
      "id": "d05d66a8-6f11-4c8b-ac88-78f72341bd0c",
      "name": "lover",
      "userType": "NORMAL",
      "profileUrl": "https://cdn.fakercloud.com/avatars/okandungel_128.jpg"
    },
    {
      "id": "a2c88a9a-606c-45e6-84c9-e37b5afba9b7",
      "name": "lover",
      "userType": "NORMAL",
      "profileUrl": "https://cdn.fakercloud.com/avatars/okandungel_128.jpg"
    },
    {
      "id": "c2250cd3-d76e-455c-8f5f-75b247e6997b",
      "name": "lover",
      "userType": "NORMAL",
      "profileUrl": "https://cdn.fakercloud.com/avatars/okandungel_128.jpg"
    },
    {
      "id": "513f8df6-485f-4ed5-b8bd-bfe6a4e3eb34",
      "name": "lover",
      "userType": "NORMAL",
      "profileUrl": "https://cdn.fakercloud.com/avatars/okandungel_128.jpg"
    },
    {
      "id": "7617150f-9ad4-41cd-a425-14486c577d53",
      "name": "lover",
      "userType": "NORMAL",
      "profileUrl": "https://cdn.fakercloud.com/avatars/okandungel_128.jpg"
    },
    {
      "id": "d95882bb-6686-4303-8628-9e4e439cb453",
      "name": "lover",
      "userType": "NORMAL",
      "profileUrl": "https://cdn.fakercloud.com/avatars/okandungel_128.jpg"
    },
    {
      "id": "9e481875-23e3-4ebf-9466-4273de5c1120",
      "name": "lover",
      "userType": "NORMAL",
      "profileUrl": "https://cdn.fakercloud.com/avatars/okandungel_128.jpg"
    },
    {
      "id": "c7d3c903-8e0f-4a0c-bb40-5a929233cca6",
      "name": "lover",
      "userType": "NORMAL",
      "profileUrl": "https://cdn.fakercloud.com/avatars/okandungel_128.jpg"
    },
    {
      "id": "bbfd01f0-d895-4e5d-8c86-99d9616ff4cc",
      "name": "lover",
      "userType": "NORMAL",
      "profileUrl": "https://cdn.fakercloud.com/avatars/okandungel_128.jpg"
    },
    {
      "id": "b61cc07c-a1bf-4117-aaf1-c9533b147c6d",
      "name": "lover",
      "userType": "NORMAL",
      "profileUrl": "https://cdn.fakercloud.com/avatars/okandungel_128.jpg"
    },
    {
      "id": "55f440d1-c04c-45a6-9dc5-91a7c054051a",
      "name": "lover",
      "userType": "NORMAL",
      "profileUrl": "https://cdn.fakercloud.com/avatars/okandungel_128.jpg"
    },
    {
      "id": "b13e3125-0e52-4380-9f62-69fb8f17c11c",
      "name": "lover",
      "userType": "NORMAL",
      "profileUrl": "https://cdn.fakercloud.com/avatars/okandungel_128.jpg"
    },
    {
      "id": "5b92758a-ed3b-4252-ac14-a76845b73420",
      "name": "lover",
      "userType": "NORMAL",
      "profileUrl": "https://cdn.fakercloud.com/avatars/okandungel_128.jpg"
    },
    {
      "id": "e15658e6-ca42-403b-a062-86f44a963255",
      "name": "lover",
      "userType": "NORMAL",
      "profileUrl": "https://cdn.fakercloud.com/avatars/okandungel_128.jpg"
    },
    {
      "id": "0cc1787f-41a1-4a8e-9c93-ae049d421ac4",
      "name": "lover",
      "userType": "NORMAL",
      "profileUrl": "https://cdn.fakercloud.com/avatars/okandungel_128.jpg"
    },
    {
      "id": "fc322fc4-5368-45fc-87a7-6d775500c89f",
      "name": "lover",
      "userType": "NORMAL",
      "profileUrl": "https://cdn.fakercloud.com/avatars/okandungel_128.jpg"
    },
    {
      "id": "9fbf7493-31af-4564-ab1a-ea8dde52cc24",
      "name": "lover",
      "userType": "NORMAL",
      "profileUrl": "https://cdn.fakercloud.com/avatars/okandungel_128.jpg"
    },
    {
      "id": "9b8d0f1d-616f-48c3-a424-7340c7e66c0c",
      "name": "lover",
      "userType": "NORMAL",
      "profileUrl": "https://cdn.fakercloud.com/avatars/okandungel_128.jpg"
    },
    {
      "id": "b188a150-7ac9-4cad-89ed-f58757533577",
      "name": "lover",
      "userType": "NORMAL",
      "profileUrl": "https://cdn.fakercloud.com/avatars/okandungel_128.jpg"
    },
    {
      "id": "181cc706-9520-4576-8b04-7714bc55601d",
      "name": "lover",
      "userType": "NORMAL",
      "profileUrl": "https://cdn.fakercloud.com/avatars/okandungel_128.jpg"
    },
    {
      "id": "51c24b5c-ef16-460a-a60b-8463db267a1c",
      "name": "lover",
      "userType": "NORMAL",
      "profileUrl": "https://cdn.fakercloud.com/avatars/okandungel_128.jpg"
    },
    {
      "id": "8df51ec0-11a4-4056-bc92-b1f447720168",
      "name": "lover",
      "userType": "NORMAL",
      "profileUrl": "https://cdn.fakercloud.com/avatars/okandungel_128.jpg"
    },
    {
      "id": "b3abec80-0191-49e1-88b9-c87180cf011f",
      "name": "lover",
      "userType": "NORMAL",
      "profileUrl": "https://cdn.fakercloud.com/avatars/okandungel_128.jpg"
    },
    {
      "id": "741501db-8728-42ae-92c1-a6f3676bb541",
      "name": "lover",
      "userType": "NORMAL",
      "profileUrl": "https://cdn.fakercloud.com/avatars/okandungel_128.jpg"
    },
    {
      "id": "3c0e6571-cad0-47c2-914d-126cf06bc35e",
      "name": "lover",
      "userType": "NORMAL",
      "profileUrl": "https://cdn.fakercloud.com/avatars/okandungel_128.jpg"
    },
    {
      "id": "26caf2f3-b485-4119-adab-95b7f1b5fbba",
      "name": "lover",
      "userType": "NORMAL",
      "profileUrl": "https://cdn.fakercloud.com/avatars/okandungel_128.jpg"
    },
    {
      "id": "62e51401-89e4-450d-a52a-9d01588e55ed",
      "name": "lover",
      "userType": "NORMAL",
      "profileUrl": "https://cdn.fakercloud.com/avatars/okandungel_128.jpg"
    },
    {
      "id": "6b04b796-6fba-49c2-8a47-615aaabf73c1",
      "name": "lover",
      "userType": "NORMAL",
      "profileUrl": "https://cdn.fakercloud.com/avatars/okandungel_128.jpg"
    },
    {
      "id": "7035192c-3a12-4536-ba80-3c193d408412",
      "name": "lover",
      "userType": "NORMAL",
      "profileUrl": "https://cdn.fakercloud.com/avatars/okandungel_128.jpg"
    },
    {
      "id": "2d0ec220-4297-4b94-84f9-5b8520d41801",
      "name": "lover",
      "userType": "NORMAL",
      "profileUrl": "https://cdn.fakercloud.com/avatars/okandungel_128.jpg"
    },
    {
      "id": "9f6e3b90-2c7b-4c1a-be64-1a00150bf5d0",
      "name": "lover",
      "userType": "NORMAL",
      "profileUrl": "https://cdn.fakercloud.com/avatars/okandungel_128.jpg"
    },
    {
      "id": "97f379ba-4cdc-4970-a744-161f9981f243",
      "name": "lover",
      "userType": "NORMAL",
      "profileUrl": "https://cdn.fakercloud.com/avatars/okandungel_128.jpg"
    },
    {
      "id": "b02221d1-a38d-4040-a9a4-ba9adc963900",
      "name": "lover",
      "userType": "NORMAL",
      "profileUrl": "https://cdn.fakercloud.com/avatars/okandungel_128.jpg"
    },
    {
      "id": "fc5e84a0-a053-4b7b-9dee-7f830588ff5c",
      "name": "lover",
      "userType": "NORMAL",
      "profileUrl": "https://cdn.fakercloud.com/avatars/okandungel_128.jpg"
    },
    {
      "id": "bca73bf1-6f81-4b1c-a537-24e18b14884f",
      "name": "lover",
      "userType": "NORMAL",
      "profileUrl": "https://cdn.fakercloud.com/avatars/okandungel_128.jpg"
    },
    {
      "id": "6b68e454-dab9-4242-9c7c-649c99a8b89b",
      "name": "lover",
      "userType": "NORMAL",
      "profileUrl": "https://cdn.fakercloud.com/avatars/okandungel_128.jpg"
    },
    {
      "id": "26a05ad7-c39d-4d5e-8579-0e1d1922938d",
      "name": "lover",
      "userType": "NORMAL",
      "profileUrl": "https://cdn.fakercloud.com/avatars/okandungel_128.jpg"
    },
    {
      "id": "b98b5523-c1cb-413a-9516-0cb346e18ada",
      "name": "lover",
      "userType": "NORMAL",
      "profileUrl": "https://cdn.fakercloud.com/avatars/okandungel_128.jpg"
    }
  ],
  "gilberts": [],
  "matches": []
}